request_listener/__main__.py
request_listener/app.py
request_listener-0.1.0.dist-info/WHEEL
request_listener-0.1.0.dist-info/METADATA
request_listener-0.1.0.dist-info/RECORD
